LICENSE
README.md
setup.py
isAPIup/__init__.py
isAPIup/isAPIup.py
isAPIup.egg-info/PKG-INFO
isAPIup.egg-info/SOURCES.txt
isAPIup.egg-info/dependency_links.txt
isAPIup.egg-info/requires.txt
isAPIup.egg-info/top_level.txt
test/test_isAPIup.py
test/test_urls.py