Metadata-Version: 2.1
Name: isAPIup
Version: 0.0.5
Summary: isAPIup is a Length based API testing and monitoring library
Home-page: https://github.com/Sandeeppushp/isAPIup
Author: Sandeep Pushp
Author-email: sandeepkumarpushp@gmail.com
License: MIT
Platform: UNKNOWN
Classifier: License :: OSI Approved :: MIT License
Classifier: Programming Language :: Python :: 3
Classifier: Programming Language :: Python :: 3.7
Requires-Python: >=3.2
License-File: LICENSE
